olive/__init__.py
olive/metadata.py
olive-0.2.11.dist-info/METADATA
olive-0.2.11.dist-info/WHEEL
olive-0.2.11.dist-info/top_level.txt
olive-0.2.11.dist-info/RECORD
