Metadata-Version: 2.1
Name: olive
Version: 0.2.11
Summary: a python wrapper for an AIS Database API
Home-page: https://github.com/GeoBigData/AISDatabase
Author: Elizabeth Golden
Author-email: elizabeth.golden@digitalglobe.com
License: UNKNOWN
Platform: UNKNOWN
Requires-Python: >=3
Requires-Dist: requests
Requires-Dist: python-dotenv
